casting/discord/framework/__init__.py
casting/discord/framework/__main__.py
casting/discord/framework/api.py
casting/discord/framework/discord_adapter/__init__.py
casting/discord/framework/discord_adapter/bot_app.py
casting/discord/framework/discord_adapter/components.py
casting/discord/framework/discord_adapter/config.py
casting/discord/framework/discord_adapter/context.py
casting/discord/framework/discord_adapter/context_collector.py
casting/discord/framework/discord_adapter/session_manager.py
casting/discord/framework/models.py
casting/discord/framework/protocol.py
casting/discord/framework/runtime.py
casting/discord/framework/testing/__init__.py
casting/discord/framework/testing/config.py
casting/discord/framework/testing/env_manager.py
casting/discord/framework/testing/harness.py
casting/discord/framework/testing/runner.py
casting/discord/framework/toolkit.py
casting_discord_framework-0.1.0.dist-info/WHEEL
casting_discord_framework-0.1.0.dist-info/entry_points.txt
casting_discord_framework-0.1.0.dist-info/METADATA
casting_discord_framework-0.1.0.dist-info/RECORD
