Metadata-Version: 2.3
Name: casting-discord-framework
Version: 0.1.0
Summary: Discord adapter framework for AI at D3
Requires-Dist: discord-py>=2.4.0
Requires-Dist: python-dotenv>=1.0.1
Requires-Dist: llmgine
Requires-Python: >=3.13
